.DS_Store
auto_extract/__init__.py
auto_extract/classify_organisation.py
auto_extract/extract_SDG.py
auto_extract/extract_persons.py
auto_extract/extract_related_orgs.py
auto_extract/preprocessing.py
auto_extract/read_pdf.py
auto_extract/run_auto_extract.py
nedextract/__init__.py
nedextract/classify_organisation.py
nedextract/extract_persons.py
nedextract/extract_related_orgs.py
nedextract/preprocessing.py
nedextract/read_pdf.py
nedextract/run_nedextract.py
nedextract/utils/__init__.py
nedextract/utils/determinejobs.py
nedextract/utils/keywords.py
nedextract/utils/nameanalysis.py
nedextract/utils/orgs_checks.py
nedextract-0.2.1.dist-info/LICENSE
nedextract-0.2.1.dist-info/METADATA
nedextract-0.2.1.dist-info/NOTICE
nedextract-0.2.1.dist-info/WHEEL
nedextract-0.2.1.dist-info/top_level.txt
nedextract-0.2.1.dist-info/RECORD
