Metadata-Version: 2.1
Name: nedextract
Version: 0.2.1
Summary: extract specific information from annual report files
Home-page: https://github.com/Transparency-in-the-non-profit-sector/nedextract
Author: Laura Ootes
Author-email: l.ootes@esciencecenter.nl
Project-URL: Bug Tracker, https://github.com/Transparency-in-the-non-profit-sector/nedextract/issues
Keywords: NLP,Philanthropy
Classifier: Development Status :: 2 - Pre-Alpha
Classifier: Intended Audience :: Developers
Classifier: License :: OSI Approved :: Apache Software License
Classifier: Natural Language :: English
Classifier: Programming Language :: Python :: 3
Classifier: Programming Language :: Python :: 3.8
Classifier: Programming Language :: Python :: 3.9
Classifier: Programming Language :: Python :: 3.10
Classifier: Programming Language :: Python :: 3.11
Requires-Python: >=3.8
License-File: LICENSE
License-File: NOTICE
Requires-Dist: numpy
Requires-Dist: pandas
Requires-Dist: stanza
Requires-Dist: fuzzywuzzy
Requires-Dist: pdftotext
Requires-Dist: python-Levenshtein
Requires-Dist: scikit-learn
Requires-Dist: openpyxl
Requires-Dist: xlsxwriter
Provides-Extra: dev
Requires-Dist: bump2version ; extra == 'dev'
Requires-Dist: prospector[with_pyroma] ; extra == 'dev'
Requires-Dist: isort ; extra == 'dev'
Requires-Dist: pytest ; extra == 'dev'
Requires-Dist: pytest-cov ; extra == 'dev'
Requires-Dist: sphinx ; extra == 'dev'
Requires-Dist: sphinx-rtd-theme ; extra == 'dev'
Requires-Dist: sphinx-autoapi ; extra == 'dev'
Provides-Extra: publishing
Requires-Dist: twine ; extra == 'publishing'
Requires-Dist: wheel ; extra == 'publishing'
